setup.py
looker_client/__init__.py
looker_client/looker_client.py
looker_client.egg-info/PKG-INFO
looker_client.egg-info/SOURCES.txt
looker_client.egg-info/dependency_links.txt
looker_client.egg-info/requires.txt
looker_client.egg-info/top_level.txt