Metadata-Version: 1.0
Name: looker-client
Version: 0.1
Summary: Looker 3 API for Python
Home-page: https://github.com/schwallie2/looker3_api
Author: Chase Schwalbach
Author-email: schwallie@gmail.com
License: GNU
Keywords: python looker api 3
Platform: UNKNOWN
